sky-excel/__init__.py
sky-excel/main.py
sky-excel/main/__init__.py
sky-excel/main/body_parser.py
sky-excel/main/excel_exporter.py
sky-excel/main/header_parser.py
sky-excel/main/parsed_cell.py
sky-excel/templet/__init__.py
sky-excel/utils/__init__.py
sky-excel/utils/j_config.py
sky-excel/utils/j_dict.py
sky-excel/utils/j_params.py
sky_excel/__init__.py
sky_excel/run_main.py
sky_excel/main/__init__.py
sky_excel/main/body_parser.py
sky_excel/main/excel_exporter.py
sky_excel/main/header_copy.py
sky_excel/main/header_parser.py
sky_excel/main/parsed_cell.py
sky_excel/main/v1/__init__.py
sky_excel/main/v1/body_parser.py
sky_excel/main/v1/excel_exporter.py
sky_excel/main/v1/parsed_cell.py
sky_excel/main/v2/__init__.py
sky_excel/main/v2/excel_exporter.py
sky_excel/templet/__init__.py
sky_excel/utils/__init__.py
sky_excel/utils/j_config.py
sky_excel/utils/j_dict.py
sky_excel/utils/j_params.py
sky_excel-1.0.7.dist-info/METADATA
sky_excel-1.0.7.dist-info/WHEEL
sky_excel-1.0.7.dist-info/top_level.txt
sky_excel-1.0.7.dist-info/RECORD
