Metadata-Version: 2.1
Name: sky-excel
Version: 1.0.7
Summary: excel模板配置化导出模块
Home-page: UNKNOWN
Author: 孙楷炎
Author-email: sky483@163.com
Maintainer: 孙楷炎
Maintainer-email: sky4834@163.com
License: apache 3.0
Platform: UNKNOWN
Requires-Dist: openpyxl
Requires-Dist: xlutils
